ut_course_catalog/__init__.py
ut_course_catalog/__main__.py
ut_course_catalog/analysis.py
ut_course_catalog/cli.py
ut_course_catalog/common.py
ut_course_catalog/ja.py
ut_course_catalog/pandas.py
ut_course_catalog/py.typed
ut_course_catalog-0.2.25.dist-info/LICENSE
ut_course_catalog-0.2.25.dist-info/METADATA
ut_course_catalog-0.2.25.dist-info/WHEEL
ut_course_catalog-0.2.25.dist-info/entry_points.txt
ut_course_catalog-0.2.25.dist-info/RECORD
