Metadata-Version: 2.1
Name: ut-course-catalog
Version: 0.2.25
Summary: Python package for fetching UTokyo Online Course Catalogue
Home-page: https://github.com/34j/ut-course-catalog
License: MIT
Author: 34j
Author-email: 34j.95a2p@simplelogin.com
Requires-Python: >=3.9,<3.13
Classifier: Development Status :: 2 - Pre-Alpha
Classifier: Intended Audience :: Developers
Classifier: License :: OSI Approved :: MIT License
Classifier: Natural Language :: English
Classifier: Operating System :: OS Independent
Classifier: Programming Language :: Python :: 3
Classifier: Programming Language :: Python :: 3.9
Classifier: Programming Language :: Python :: 3.10
Classifier: Programming Language :: Python :: 3.11
Classifier: Programming Language :: Python :: 3.12
Classifier: Topic :: Software Development :: Libraries
Requires-Dist: aiofiles (>=23.2.1,<24.0.0)
Requires-Dist: aiohttp (>=3.8.6,<4.0.0)
Requires-Dist: aiohttp-client-cache[all] (>=0.12.0,<0.13.0)
Requires-Dist: beautifulsoup4 (>=4.12.2,<5.0.0)
Requires-Dist: click (>=8.1.7,<9.0.0)
Requires-Dist: pandas (>=2.1.1,<3.0.0)
Requires-Dist: rich (>=13.6.0,<14.0.0)
Requires-Dist: tenacity (>=8.2.3,<9.0.0)
Requires-Dist: tqdm (>=4.66.1,<5.0.0)
Project-URL: Bug Tracker, https://github.com/34j/ut-course-catalog/issues
Project-URL: Changelog, https://github.com/34j/ut-course-catalog/blob/main/CHANGELOG.md
Project-URL: Documentation, https://ut-course-catalog.readthedocs.io
Project-URL: Repository, https://github.com/34j/ut-course-catalog
